moneta_scheduler-1.0.0b1.dist-info/top_level.txt
moneta_scheduler-1.0.0b1.dist-info/RECORD
moneta_scheduler-1.0.0b1.dist-info/METADATA
moneta_scheduler-1.0.0b1.dist-info/DESCRIPTION.rst
moneta_scheduler-1.0.0b1.dist-info/entry_points.txt
moneta_scheduler-1.0.0b1.dist-info/metadata.json
moneta_scheduler-1.0.0b1.dist-info/WHEEL
moneta/cluster.py
moneta/server.py
moneta/moneta.py
moneta/scheduler.py
moneta/__init__.py
moneta/schedule.py
moneta/http/client.py
moneta/http/server.py
moneta/http/http.py
moneta/http/__init__.py
