Metadata-Version: 2.0
Name: moneta-scheduler
Version: 1.0.0b1
Summary: Distributed tasks scheduler
Home-page: https://github.com/geneanet/moneta
Author: Herve BRY
Author-email: herve.bry@geneanet.org
License: BSD
Keywords: cron cluster distributed task scheduler
Platform: UNKNOWN
Classifier: Development Status :: 4 - Beta
Classifier: Intended Audience :: System Administrators
Classifier: Topic :: System :: Distributed Computing
Classifier: License :: OSI Approved :: BSD License
Classifier: Programming Language :: Python :: 2.7
Requires-Dist: gevent
Requires-Dist: kazoo
Requires-Dist: pytz
